untp/__init__.py
untp/dataparse.py
untp/pvr.py
untp/untp.py
untp-1.1.8.dist-info/LICENSE.txt
untp-1.1.8.dist-info/METADATA
untp-1.1.8.dist-info/WHEEL
untp-1.1.8.dist-info/entry_points.txt
untp-1.1.8.dist-info/top_level.txt
untp-1.1.8.dist-info/RECORD
