Metadata-Version: 2.1
Name: untp
Version: 1.1.8
Summary: A command line tool to split TexturePacker published files.
Home-page: https://github.com/justbilt/untp
Author: justbilt
Author-email: wangbilt@gmail.com
License: MIT License
Keywords: untp texturepacker cocos
Platform: UNKNOWN
Classifier: Development Status :: 3 - Alpha
Classifier: Intended Audience :: Developers
Classifier: Topic :: Software Development
Classifier: License :: OSI Approved :: MIT License
Classifier: Programming Language :: Python :: 2
Classifier: Programming Language :: Python :: 2.7
Classifier: Programming Language :: Python :: 3
Classifier: Programming Language :: Python :: 3.3
Classifier: Programming Language :: Python :: 3.4
Classifier: Programming Language :: Python :: 3.5
Classifier: Programming Language :: Python :: 3.6
Classifier: Programming Language :: Python :: 3.7
Classifier: Programming Language :: Python :: 3.8
Requires-Dist: Pillow
Requires-Dist: parse
